touch_sdk/__init__.py
touch_sdk/gatt_scanner.py
touch_sdk/stream_watch.py
touch_sdk/utils.py
touch_sdk/uuids.py
touch_sdk/watch.py
touch_sdk/watch_connector.py
touch_sdk/protobuf/__init__.py
touch_sdk/protobuf/common_pb2.py
touch_sdk/protobuf/watch_input_pb2.py
touch_sdk/protobuf/watch_output_pb2.py
touch_sdk-0.8.0.dist-info/METADATA
touch_sdk-0.8.0.dist-info/WHEEL
touch_sdk-0.8.0.dist-info/licenses/LICENSE
touch_sdk-0.8.0.dist-info/RECORD
