Metadata-Version: 2.4
Name: touch-sdk
Version: 0.8.0
Summary: Doublepoint Touch SDK
Project-URL: Homepage, https://github.com/doublepointlab/touch-sdk-py#readme
Project-URL: Bug Tracker, https://github.com/doublepointlab/touch-sdk-py/issues
Author-email: Doublepoint <developer@doublepoint.com>
License: ISC License
License-File: LICENSE
Keywords: bluetooth
Classifier: Development Status :: 3 - Alpha
Classifier: Intended Audience :: Developers
Classifier: License :: OSI Approved :: ISC License (ISCL)
Classifier: Operating System :: Android
Classifier: Operating System :: MacOS :: MacOS X
Classifier: Operating System :: Microsoft :: Windows :: Windows 10
Classifier: Operating System :: POSIX :: Linux
Classifier: Topic :: Scientific/Engineering :: Bio-Informatics
Classifier: Topic :: Scientific/Engineering :: Human Machine Interfaces
Requires-Python: >=3.9
Requires-Dist: asyncio-atexit~=1.0.1
Requires-Dist: bleak~=0.22.2
Requires-Dist: protobuf~=5.28.2
